easierai_trainer_library/__init__.py
easierai_trainer_library/easierai_trainer_lib.py
easierai_trainer_library-0.1.72.dist-info/LICENSE
easierai_trainer_library-0.1.72.dist-info/METADATA
easierai_trainer_library-0.1.72.dist-info/WHEEL
easierai_trainer_library-0.1.72.dist-info/top_level.txt
easierai_trainer_library-0.1.72.dist-info/RECORD
