Metadata-Version: 2.1
Name: easierai-trainer-library
Version: 0.1.72
Summary: This library contains AI code for training purposes.
Home-page: https://scm.atosresearch.eu/ari/easier/trainer-library
Author: AIR Unit
Author-email: adrian.arroyo@atos.net
License: ATOS
Platform: UNKNOWN
Requires-Dist: flask
Requires-Dist: flask-api
Requires-Dist: flask-monitoringdashboard
Requires-Dist: sklearn
Requires-Dist: easierai-elasticsearchlib
Requires-Dist: easierai-common-functions
Requires-Dist: tensorflow
Requires-Dist: configparser
Requires-Dist: numpy
Requires-Dist: pandas (==1.2.3)
Requires-Dist: joblib
Requires-Dist: keras
Requires-Dist: datetime
Requires-Dist: pydash
Requires-Dist: phased-lstm-keras
Requires-Dist: schedule
Requires-Dist: minio
Requires-Dist: modin[ray]
